llmrecsys/__init__.py
llmrecsys/recengine.py
llmrecsys-0.0.1.dist-info/METADATA
llmrecsys-0.0.1.dist-info/WHEEL
llmrecsys-0.0.1.dist-info/licenses/LICENSE
llmrecsys-0.0.1.dist-info/RECORD
