Metadata-Version: 2.1
Name: llmrecsys
Version: 0.0.1
Summary: Recommendation systems with LLMs from Shaped.ai
Project-URL: Homepage, https://github.com/shaped-ai/llmrecsys
Project-URL: Bug Tracker, https://github.com/shaped-ai/llmrecsys/issues
Author-email: Georgiy Skovorodnikov <georgiysk@shaped.ai>
License: Copyright 2023 - Shaped.ai team. All rights reserved.
License-File: LICENSE
Keywords: AI,inference,llm,recommendations,recsys
Classifier: Development Status :: 3 - Alpha
Classifier: Operating System :: OS Independent
Classifier: Programming Language :: Python :: 3
Requires-Python: >=3.8
